Safupy/__init__.py
Safupy/safupy.py
SafuPy-0.0.1.dist-info/LICENSE
SafuPy-0.0.1.dist-info/METADATA
SafuPy-0.0.1.dist-info/WHEEL
SafuPy-0.0.1.dist-info/top_level.txt
SafuPy-0.0.1.dist-info/RECORD
