Metadata-Version: 2.1
Name: SafuPy
Version: 0.0.1
Summary: Python module which provides password hashing and any other user data encryption and decryption.
Home-page: https://gitlab.com/larryare/safupy
Author: Laurynas Kerežius
Author-email: gitlab@kerezius.lt
License: UNKNOWN
Platform: UNKNOWN
Classifier: Programming Language :: Python :: 3
Classifier: License :: OSI Approved :: GNU Affero General Public License v3
Classifier: Topic :: Security :: Cryptography
Classifier: Operating System :: OS Independent
Requires-Python: >=3.7
License-File: LICENSE
